{
    "imports": {
      "react": "https://cdn.jsdelivr.net/npm/react@17.0.2/umd/react.production.min.js",
       "react-dom": "https://cdn.jsdelivr.net/npm/react-dom@17.0.2/umd/react-dom.production.min.js",
      "single-spa": "https://cdn.jsdelivr.net/npm/single-spa@5.9.0/lib/system/single-spa.min.js",
      "@jsanz1209/root-config": "https://d22brqasyepvst.cloudfront.net/jsanz1209-root-config.js",
      "@jsanz1209/mf-product": "https://d22brqasyepvst.cloudfront.net/app2/team-product-mf-product.js?",
      "@jsanz1209/mf-header": "https://d22brqasyepvst.cloudfront.net/app1/main.js"
    }
  }